logarhythm/__init__.py
logarhythm/levels.py
logarhythm/logarhythm.py
tests/__init__.py
tests/test_logarhythm.py
logarhythm-1.0.5.dist-info/LICENSE
logarhythm-1.0.5.dist-info/METADATA
logarhythm-1.0.5.dist-info/WHEEL
logarhythm-1.0.5.dist-info/top_level.txt
logarhythm-1.0.5.dist-info/RECORD
