Metadata-Version: 2.1
Name: logarhythm
Version: 1.0.5
Summary: Simplified logging, debugging, and troubleshooting
Home-page: https://github.com/_/logarhythm
Author: Matthew Miguel
Author-email: mmiguel6288code@gmail.com
Maintainer: Matthew Miguel
Maintainer-email: mmiguel6288code@gmail.com
License: MIT
Keywords: logging,debugging,telemetry,postmortem,autodebug,interactive,monitoring,profiling,easier,log,simplified,logarhythm,logger,loggers
Platform: UNKNOWN
Classifier: Intended Audience :: Developers
Classifier: License :: OSI Approved :: MIT License
Classifier: Natural Language :: English
Classifier: Operating System :: OS Independent
Classifier: Programming Language :: Python :: 2.7
Classifier: Programming Language :: Python :: 3.5
Classifier: Programming Language :: Python :: Implementation :: CPython
Classifier: Programming Language :: Python :: Implementation :: PyPy
